llama_index/agent/llm_compiler/__init__.py
llama_index/agent/llm_compiler/output_parser.py
llama_index/agent/llm_compiler/prompts.py
llama_index/agent/llm_compiler/schema.py
llama_index/agent/llm_compiler/step.py
llama_index/agent/llm_compiler/task_fetching_unit.py
llama_index/agent/llm_compiler/utils.py
llama_index_agent_llm_compiler-0.3.2.dist-info/METADATA
llama_index_agent_llm_compiler-0.3.2.dist-info/WHEEL
llama_index_agent_llm_compiler-0.3.2.dist-info/licenses/LICENSE
llama_index_agent_llm_compiler-0.3.2.dist-info/RECORD
